hdl/config.vh
// =========================================================================
// Arquivo: hdl/config.vh
// Descrição: Parâmetros globais, macros e definições da Rede SPIN
// =========================================================================

`ifndef CONFIG_VH
`define CONFIG_VH

// =========================================================================
// ENLACE SPIN (SPIN LINK)
// =========================================================================
// O enlace SPIN é composto por dois canais bidirecionais, permitindo
// tráfego simultâneo em ambas as direções (full-duplex).
//
// A interface física de comunicação exige 38 bits por sentido, divididos em:
// ! 32 bits: dado (payload) ou cabeçalho de roteamento
// ! 4 bits: enquadramento (BP/EP), paridade e erro (formando um canal de 36 bits)
// ! 2 bits: controle de fluxo (1 bit de validação 'dv' e 1 bit de crédito 'cr')
//
// FORMATO DO PACOTE (Comutação Wormhole):
// - A comunicação ocorre por pacotes de tamanho variável.
// - A primeira palavra (Header) ativa a flag BP e contém:
//     * Bits [31:11]: Informações do protocolo / VCI
//     * Bits [9:0]: Endereço do Destino (necessário para rotear na árvore)
// - As palavras intermediárias (Payload) carregam apenas dados brutos.
// - A última palavra do pacote ativa a flag EP (End of Packet).
// =========================================================================

// -------------------------------------------------------------------------
// Larguras dos barramentos (Canal de 36 bits de dados + tag)

// +---+---+---+---+------------------------+------+---------------+
// | x | x | 0 | 1 |   Protocolo (31-11)    | flag | Destino (9-0) |
// +---+---+---+---+------------------------+------+---------------+

// +---+---+---+---+-----------------------------------------------+
// | x | x | 0 | 0 |                 Dado (31-0)                   |
// +---+---+---+---+-----------------------------------------------+

// +---+---+---+---+-----------------------------------------------+
// | x | x | 0 | 0 |                 Dado (31-0)                   |
// +---+---+---+---+-----------------------------------------------+

//                               ...

// +---+---+---+---+-----------------------------------------------+
// | x | x | 1 | 0 |                 Dado (31-0)                   |
// +---+---+---+---+-----------------------------------------------+

`define SPIN_DATA_W     32  // Largura da carga útil (dados brutos)
`define SPIN_TAG_W      4   // Largura das flags de acompanhamento
`define SPIN_CHANNEL_W  36  // Canal principal (Dado + Tag) que viaja pelas FIFOs

// -------------------------------------------------------------------------
// Posições dos bits na TAG de 4 bits (Enquadramento, Paridade e Erro)
// -------------------------------------------------------------------------
`define TAG_BP_BIT      0   // Início de pacote (Begin Packet)
`define TAG_EP_BIT      1   // Fim de pacote (End of Packet)
`define TAG_PAR_BIT     2   // Bit de paridade
`define TAG_ERR_BIT     3   // Sinalização de erro de transmissão

// -------------------------------------------------------------------------
// Constantes de Roteamento e Formato do Cabeçalho
// -------------------------------------------------------------------------
`define ROUTE_DEST_W    10  // Largura do campo de endereço de destino (Bits 9 a 0)

//TODO: Revisar maquinas de estado e utilidade disso aqui
// -------------------------------------------------------------------------
// Estados Úteis (Opcional - para Máquinas de Estado)
// -------------------------------------------------------------------------
// Constantes lógicas para facilitar a leitura do código
`define HIGH            1'b1
`define LOW             1'b0

`endif // CONFIG_VH

hdl/fifo.v
// =========================================================================
// Arquivo: hdl/fifo.v
// Descrição: FIFO genérica circular e parametrizável para a Rede SPIN
// =========================================================================

`include "hdl/config.vh"

module fifo #(
    parameter DEPTH = 4,               // Profundidade padrão para UP/DN
    parameter WIDTH = `SPIN_CHANNEL_W  // 36 bits definido no config.vh
) (
    input wire clk,
    input wire rst,

    // Interface de Escrita
    input wire             write_en,
    input wire [WIDTH-1:0] data_in,

    // Interface de Leitura
    input  wire             read_en,
    output reg  [WIDTH-1:0] data_out,

    // Sinais de Estado
    output wire full,
    output wire empty

    //Largura dos ponteiros

);
    // Função interna do Verilog-2001 para calcular a largura dos ponteiros
    localparam PTR_WIDTH = $clog2(DEPTH);
    //Define o valor máximo do ponteiro com a largura exata
    localparam [PTR_WIDTH-1:0] MAX_PTR = PTR_WIDTH'(DEPTH - 1);
    // Array de memória
    reg [WIDTH-1:0] mem[0:DEPTH-1];

    // Ponteiros de leitura e escrita
    reg [PTR_WIDTH-1:0] rptr;
    reg [PTR_WIDTH-1:0] wptr;

    // O tamanho do contador deve acomodar o valor máximo DEPTH
    reg [PTR_WIDTH:0] count;

    // Atribuições contínuas para as flags
    assign full  = (count == DEPTH);
    assign empty = (count == 0);

    // Bloco sequencial para controle da FIFO
    always @(posedge clk) begin
        if (rst) begin
            wptr <= 0;
            rptr <= 0;
            count <= 0;
            data_out <= 0;
        end else begin
            // ----------------------------------------------------
            // Lógica de Leitura e Escrita Simultânea
            // ----------------------------------------------------
            case ({
                write_en && !full, read_en && !empty
            })

                2'b10: begin  // Apenas Escrita
                    mem[wptr] <= data_in;
                    // Lógica circular do ponteiro
                    wptr <= (wptr == MAX_PTR) ? 0 : wptr + 1;
                    count <= count + 1;
                end

                2'b01: begin  // Apenas Leitura
                    data_out <= mem[rptr];
                    rptr <= (rptr == MAX_PTR) ? 0 : rptr + 1;
                    count <= count - 1;
                end

                2'b11: begin  // Escrita e Leitura
                    mem[wptr] <= data_in;
                    data_out <= mem[rptr];

                    wptr <= (wptr == MAX_PTR) ? 0 : wptr + 1;
                    rptr <= (rptr == MAX_PTR) ? 0 : rptr + 1;
                    // count se mantém igual, pois entrou 1 e saiu 1
                end

                default: begin
                end
            endcase
        end
    end

endmodule

test/tb_fifo.v
// =========================================================================
// Arquivo: test/tb_fifo.v
// Descricao: Testbench AUTO-VERIFICAVEL da FIFO.
//
//   Conceito de verificacao: o proprio testbench conhece o resultado esperado,
//   compara com o que o DUT produziu, CONTA os erros e imprime um veredito no
//   final. A forma de onda (fifo.vcd) e so para depurar quando algo falha.
//
//   Cobre, no DUT de profundidade 4:
//     T0 reset            T1 encher+ordem        T2 guardas overflow/underflow
//     T3 leitura+escrita simultaneas (caso 2'b11)
//     T4 wraparound circular (ponteiros cruzam MAX_PTR e voltam a 0)
//   E, num segundo DUT de profundidade 18 (NAO potencia de 2), valida que o
//   wrap e 17->0 (e nao 31->0 do estouro binario ingenuo).
//
//   Detalhe de timing: a leitura e REGISTRADA (data_out so atualiza no ciclo
//   seguinte ao read_en). Por isso dirigimos estimulo na borda de DESCIDA e
//   conferimos data_out depois da borda de subida que efetiva a leitura.
//
//   Rode a partir da RAIZ do projeto:
//     iverilog -g2012 -o simulation/sim_fifo hdl/fifo.v test/tb_fifo.v
//     vvp simulation/sim_fifo
// =========================================================================

`timescale 1ns/1ps
`include "hdl/config.vh"

module tb_fifo;
    localparam W = `SPIN_CHANNEL_W;

    reg clk = 0, rst = 1;
    integer errors = 0;

    // ---- DUT de profundidade 4 ----
    reg              we4 = 0, re4 = 0;
    reg  [W-1:0]     din4 = 0;
    wire [W-1:0]     dout4;
    wire             full4, empty4;
    fifo #(.DEPTH(4), .WIDTH(W)) dut4 (
        .clk(clk), .rst(rst), .write_en(we4), .data_in(din4),
        .read_en(re4), .data_out(dout4), .full(full4), .empty(empty4));

    // ---- DUT de profundidade 18 (testa wrap nao-potencia-de-2) ----
    reg              we18 = 0, re18 = 0;
    reg  [W-1:0]     din18 = 0;
    wire [W-1:0]     dout18;
    wire             full18, empty18;
    fifo #(.DEPTH(18), .WIDTH(W)) dut18 (
        .clk(clk), .rst(rst), .write_en(we18), .data_in(din18),
        .read_en(re18), .data_out(dout18), .full(full18), .empty(empty18));

    always #5 clk = ~clk;

    initial begin $dumpfile("fifo.vcd"); $dumpvars(0, tb_fifo); end
    initial begin #20000 $display(">>> TIMEOUT"); $finish; end

    // ---- helpers de verificacao ----
    task chk(input [W-1:0] got, input [W-1:0] exp, input [511:0] msg);
    begin
        if (got !== exp) begin
            $display("  FALHA %0s: got=%h exp=%h @t=%0t", msg, got, exp, $time);
            errors = errors + 1;
        end else $display("  OK    %0s = %h", msg, got);
    end endtask

    task chkb(input val, input exp, input [511:0] msg);
    begin
        if (val !== exp) begin
            $display("  FALHA %0s: %b (esp %b) @t=%0t", msg, val, exp, $time);
            errors = errors + 1;
        end else $display("  OK    %0s = %b", msg, val);
    end endtask

    // ---- tarefas para o DUT de 4 ----
    task push4(input [W-1:0] d);
    begin @(negedge clk); we4 = 1; din4 = d; @(negedge clk); we4 = 0; end endtask

    task pop4(input [W-1:0] exp);
    begin @(negedge clk); re4 = 1; @(negedge clk); re4 = 0; chk(dout4, exp, "pop4"); end endtask

    task simul4(input [W-1:0] d, input [W-1:0] exp);  // escreve e le no MESMO ciclo
    begin @(negedge clk); we4 = 1; din4 = d; re4 = 1;
          @(negedge clk); we4 = 0; re4 = 0; chk(dout4, exp, "simul4"); end endtask

    integer k;
    initial begin
        repeat (2) @(negedge clk); rst = 0;

        // ---- T0: reset ----
        $display("== T0: reset ==");
        chkb(empty4, 1'b1, "empty pos-reset");
        chkb(full4,  1'b0, "full pos-reset");

        // ---- T1: encher ate 4, conferir full, drenar conferindo ORDEM ----
        $display("== T1: encher e drenar (ordem FIFO) ==");
        push4(36'h0A); push4(36'h0B); push4(36'h0C); push4(36'h0D);
        chkb(full4, 1'b1, "full apos 4 escritas");
        pop4(36'h0A); pop4(36'h0B); pop4(36'h0C); pop4(36'h0D);
        chkb(empty4, 1'b1, "empty apos drenar");

        // ---- T2: guardas. Escrita com cheia e leitura com vazia sao ignoradas ----
        $display("== T2: guardas overflow/underflow ==");
        // tenta ler vazia: nao deve dar erro nem mudar empty
        @(negedge clk); re4 = 1; @(negedge clk); re4 = 0;
        chkb(empty4, 1'b1, "continua vazia apos ler vazia");
        // enche e tenta escrever uma 5a -> deve ser ignorada (continua 4 itens)
        push4(36'h11); push4(36'h22); push4(36'h33); push4(36'h44);
        @(negedge clk); we4 = 1; din4 = 36'hFF; @(negedge clk); we4 = 0; // 5a escrita
        chkb(full4, 1'b1, "continua cheia apos overflow");
        // drena: deve sair 11,22,33,44 (a 5a foi descartada)
        pop4(36'h11); pop4(36'h22); pop4(36'h33); pop4(36'h44);
        chkb(empty4, 1'b1, "vazia apos drenar (5a descartada)");

        // ---- T3: leitura e escrita simultaneas (count constante) ----
        $display("== T3: leitura+escrita simultaneas ==");
        push4(36'd101);
        push4(36'd102);                          // FIFO: 101,102
        simul4(36'd103, 36'd101);                // escreve 103, le 101 -> 102,103
        simul4(36'd104, 36'd102);                // escreve 104, le 102 -> 103,104
        pop4(36'd103); pop4(36'd104);
        chkb(empty4, 1'b1, "vazia apos T3");

        // ---- T4: wraparound no DUT de 4 (ponteiros cruzam 3->0) ----
        $display("== T4: wraparound (DEPTH=4) ==");
        push4(36'hA1); push4(36'hA2); push4(36'hA3); // wptr: 0,1,2->3
        pop4(36'hA1);                                 // rptr: 0->1 (restam A2,A3)
        push4(36'hA4); push4(36'hA5);                 // wptr cruza 3->0->1 (A2..A5)
        pop4(36'hA2); pop4(36'hA3); pop4(36'hA4); pop4(36'hA5);
        chkb(empty4, 1'b1, "vazia apos wrap DEPTH=4");

        // ---- T5: wraparound no DUT de 18 (valida 17->0, nao 31->0) ----
        $display("== T5: wraparound (DEPTH=18, nao potencia de 2) ==");
        for (k = 0; k < 18; k = k + 1) begin
            @(negedge clk); we18 = 1; din18 = k; @(negedge clk); we18 = 0;
        end
        chkb(full18, 1'b1, "DEPTH=18 cheia apos 18 escritas");
        for (k = 0; k < 18; k = k + 1) begin
            @(negedge clk); re18 = 1; @(negedge clk); re18 = 0;
            chk(dout18, k, "drena18");
        end
        chkb(empty18, 1'b1, "DEPTH=18 vazia apos drenar");
        // agora os ponteiros estao em 0 SE o wrap for 17->0; escreve/le mais 3
        // (se o wrap fosse 31->0, estes iriam para mem[18..20] -> X)
        for (k = 0; k < 3; k = k + 1) begin
            @(negedge clk); we18 = 1; din18 = 36'd900 + k; @(negedge clk); we18 = 0;
        end
        for (k = 0; k < 3; k = k + 1) begin
            @(negedge clk); re18 = 1; @(negedge clk); re18 = 0;
            chk(dout18, 36'd900 + k, "pos-wrap18");
        end

        // ---- veredito ----
        $display("--------------------------------");
        if (errors == 0) $display(">>> TODOS OS TESTES DA FIFO PASSARAM");
        else             $display(">>> FIFO FALHOU: %0d erro(s)", errors);
        $finish;
    end
endmodule

fifo.vcd
$date
	Sun Jun 28 02:07:36 2026
$end
$version
	Icarus Verilog
$end
$timescale
	1ps
$end
$scope module tb_fifo $end
$var wire 1 ! full4 $end
$var wire 1 " full18 $end
$var wire 1 # empty4 $end
$var wire 1 $ empty18 $end
$var wire 36 % dout4 [35:0] $end
$var wire 36 & dout18 [35:0] $end
$var parameter 32 ' W $end
$var reg 1 ( clk $end
$var reg 36 ) din18 [35:0] $end
$var reg 36 * din4 [35:0] $end
$var reg 1 + re18 $end
$var reg 1 , re4 $end
$var reg 1 - rst $end
$var reg 1 . we18 $end
$var reg 1 / we4 $end
$var integer 32 0 errors [31:0] $end
$var integer 32 1 k [31:0] $end
$scope module dut18 $end
$var wire 1 ( clk $end
$var wire 36 2 data_in [35:0] $end
$var wire 1 + read_en $end
$var wire 1 - rst $end
$var wire 1 . write_en $end
$var wire 1 " full $end
$var wire 1 $ empty $end
$var parameter 32 3 DEPTH $end
$var parameter 5 4 MAX_PTR $end
$var parameter 32 5 PTR_WIDTH $end
$var parameter 32 6 WIDTH $end
$var reg 6 7 count [5:0] $end
$var reg 36 8 data_out [35:0] $end
$var reg 5 9 rptr [4:0] $end
$var reg 5 : wptr [4:0] $end
$upscope $end
$scope module dut4 $end
$var wire 1 ( clk $end
$var wire 36 ; data_in [35:0] $end
$var wire 1 , read_en $end
$var wire 1 - rst $end
$var wire 1 / write_en $end
$var wire 1 ! full $end
$var wire 1 # empty $end
$var parameter 32 < DEPTH $end
$var parameter 2 = MAX_PTR $end
$var parameter 32 > PTR_WIDTH $end
$var parameter 32 ? WIDTH $end
$var reg 3 @ count [2:0] $end
$var reg 36 A data_out [35:0] $end
$var reg 2 B rptr [1:0] $end
$var reg 2 C wptr [1:0] $end
$upscope $end
$scope task chk $end
$var reg 36 D exp [35:0] $end
$var reg 36 E got [35:0] $end
$var reg 512 F msg [511:0] $end
$upscope $end
$scope task chkb $end
$var reg 1 G exp $end
$var reg 512 H msg [511:0] $end
$var reg 1 I val $end
$upscope $end
$scope task pop4 $end
$var reg 36 J exp [35:0] $end
$upscope $end
$scope task push4 $end
$var reg 36 K d [35:0] $end
$upscope $end
$scope task simul4 $end
$var reg 36 L d [35:0] $end
$var reg 36 M exp [35:0] $end
$upscope $end
$upscope $end
$enddefinitions $end
$comment Show the parameter values. $end
$dumpall
b100100 ?
b10 >
b11 =
b100 <
b100100 6
b101 5
b10001 4
b10010 3
b100100 '
$end
#0
$dumpvars
bx M
bx L
bx K
bx J
xI
bx H
xG
bx F
bx E
bx D
bx C
bx B
bx A
bx @
b0 ;
bx :
bx 9
bx 8
bx 7
b0 2
bx 1
b0 0
0/
0.
1-
0,
0+
b0 *
b0 )
0(
bx &
bx %
x$
x#
x"
x!
$end
#5000
0!
1#
0"
1$
b0 %
b0 A
b0 @
b0 B
b0 C
b0 &
b0 8
b0 7
b0 9
b0 :
1(
#10000
0(
#15000
1(
#20000
b1010 K
b110011001110101011011000110110000100000011100000110111101110011001011010111001001100101011100110110010101110100 H
0G
0I
0-
0(
#25000
1(
#30000
b1010 *
b1010 ;
1/
0(
#35000
0#
b1 @
b1 C
1(
#40000
b1011 K
0/
0(
#45000
1(
#50000
b1011 *
b1011 ;
1/
0(
#55000
b10 @
b10 C
1(
#60000
b1100 K
0/
0(
#65000
1(
#70000
b1100 *
b1100 ;
1/
0(
#75000
b11 @
b11 C
1(
#80000
b1101 K
0/
0(
#85000
1(
#90000
b1101 *
b1101 ;
1/
0(
#95000
1!
b100 @
b0 C
1(
#100000
b1010 J
b110011001110101011011000110110000100000011000010111000001101111011100110010000000110100001000000110010101110011011000110111001001101001011101000110000101110011 H
1G
1I
0/
0(
#105000
1(
#110000
1,
0(
#115000
0!
b11 @
b1 B
b1010 %
b1010 A
1(
#120000
b1011 J
b1110000011011110111000000110100 F
b1010 D
b1010 E
0,
0(
#125000
1(
#130000
1,
0(
#135000
b10 @
b10 B
b1011 %
b1011 A
1(
#140000
b1100 J
b1011 D
b1011 E
0,
0(
#145000
1(
#150000
1,
0(
#155000
b1 @
b11 B
b1100 %
b1100 A
1(
#160000
b1101 J
b1100 D
b1100 E
0,
0(
#165000
1(
#170000
1,
0(
#175000
1#
b0 @
b0 B
b1101 %
b1101 A
1(
#180000
b110010101101101011100000111010001111001001000000110000101110000011011110111001100100000011001000111001001100101011011100110000101110010 H
b1101 D
b1101 E
0,
0(
#185000
1(
#190000
1,
0(
#195000
1(
#200000
b10001 K
b110001101101111011011100111010001101001011011100111010101100001001000000111011001100001011110100110100101100001001000000110000101110000011011110111001100100000011011000110010101110010001000000111011001100001011110100110100101100001 H
0,
0(
#205000
1(
#210000
b10001 *
b10001 ;
1/
0(
#215000
0#
b1 @
b1 C
1(
#220000
b100010 K
0/
0(
#225000
1(
#230000
b100010 *
b100010 ;
1/
0(
#235000
b10 @
b10 C
1(
#240000
b110011 K
0/
0(
#245000
1(
#250000
b110011 *
b110011 ;
1/
0(
#255000
b11 @
b11 C
1(
#260000
b1000100 K
0/
0(
#265000
1(
#270000
b1000100 *
b1000100 ;
1/
0(
#275000
1!
b100 @
b0 C
1(
#280000
0/
0(
#285000
1(
#290000
b11111111 *
b11111111 ;
1/
0(
#295000
1(
#300000
b10001 J
b1100011011011110110111001110100011010010110111001110101011000010010000001100011011010000110010101101001011000010010000001100001011100000110111101110011001000000110111101110110011001010111001001100110011011000110111101110111 H
0/
0(
#305000
1(
#310000
1,
0(
#315000
0!
b11 @
b1 B
b10001 %
b10001 A
1(
#320000
b100010 J
b10001 D
b10001 E
0,
0(
#325000
1(
#330000
1,
0(
#335000
b10 @
b10 B
b100010 %
b100010 A
1(
#340000
b110011 J
b100010 D
b100010 E
0,
0(
#345000
1(
#350000
1,
0(
#355000
b1 @
b11 B
b110011 %
b110011 A
1(
#360000
b1000100 J
b110011 D
b110011 E
0,
0(
#365000
1(
#370000
1,
0(
#375000
1#
b0 @
b0 B
b1000100 %
b1000100 A
1(
#380000
b1100101 K
b11101100110000101111010011010010110000100100000011000010111000001101111011100110010000001100100011100100110010101101110011000010111001000100000001010000011010101100001001000000110010001100101011100110110001101100001011100100111010001100001011001000110000100101001 H
b1000100 D
b1000100 E
0,
0(
#385000
1(
#390000
b1100101 *
b1100101 ;
1/
0(
#395000
0#
b1 @
b1 C
1(
#400000
b1100110 K
0/
0(
#405000
1(
#410000
b1100110 *
b1100110 ;
1/
0(
#415000
b10 @
b10 C
1(
#420000
b1100101 M
b1100111 L
0/
0(
#425000
1(
#430000
1,
b1100111 *
b1100111 ;
1/
0(
#435000
b1 B
b11 C
b1100101 %
b1100101 A
1(
#440000
b1100110 M
b1101000 L
b11100110110100101101101011101010110110000110100 F
b1100101 D
b1100101 E
0,
0/
0(
#445000
1(
#450000
1,
b1101000 *
b1101000 ;
1/
0(
#455000
b10 B
b0 C
b1100110 %
b1100110 A
1(
#460000
b1100111 J
b1100110 D
b1100110 E
0,
0/
0(
#465000
1(
#470000
1,
0(
#475000
b1 @
b11 B
b1100111 %
b1100111 A
1(
#480000
b1101000 J
b1110000011011110111000000110100 F
b1100111 D
b1100111 E
0,
0(
#485000
1(
#490000
1,
0(
#495000
1#
b0 @
b0 B
b1101000 %
b1101000 A
1(
#500000
b10100001 K
b1110110011000010111101001101001011000010010000001100001011100000110111101110011001000000101010000110011 H
b1101000 D
b1101000 E
0,
0(
#505000
1(
#510000
b10100001 *
b10100001 ;
1/
0(
#515000
0#
b1 @
b1 C
1(
#520000
b10100010 K
0/
0(
#525000
1(
#530000
b10100010 *
b10100010 ;
1/
0(
#535000
b10 @
b10 C
1(
#540000
b10100011 K
0/
0(
#545000
1(
#550000
b10100011 *
b10100011 ;
1/
0(
#555000
b11 @
b11 C
1(
#560000
b10100001 J
0/
0(
#565000
1(
#570000
1,
0(
#575000
b10 @
b1 B
b10100001 %
b10100001 A
1(
#580000
b10100100 K
b10100001 D
b10100001 E
0,
0(
#585000
1(
#590000
b10100100 *
b10100100 ;
1/
0(
#595000
b11 @
b0 C
1(
#600000
b10100101 K
0/
0(
#605000
1(
#610000
b10100101 *
b10100101 ;
1/
0(
#615000
1!
b100 @
b1 C
1(
#620000
b10100010 J
0/
0(
#625000
1(
#630000
1,
0(
#635000
0!
b11 @
b10 B
b10100010 %
b10100010 A
1(
#640000
b10100011 J
b10100010 D
b10100010 E
0,
0(
#645000
1(
#650000
1,
0(
#655000
b10 @
b11 B
b10100011 %
b10100011 A
1(
#660000
b10100100 J
b10100011 D
b10100011 E
0,
0(
#665000
1(
#670000
1,
0(
#675000
b1 @
b0 B
b10100100 %
b10100100 A
1(
#680000
b10100101 J
b10100100 D
b10100100 E
0,
0(
#685000
1(
#690000
1,
0(
#695000
1#
b0 @
b1 B
b10100101 %
b10100101 A
1(
#700000
b0 1
b111011001100001011110100110100101100001001000000110000101110000011011110111001100100000011101110111001001100001011100000010000001000100010001010101000001010100010010000011110100110100 H
b10100101 D
b10100101 E
0,
0(
#705000
1(
#710000
1.
0(
#715000
0$
b1 7
b1 :
1(
#720000
b1 1
0.
0(
#725000
1(
#730000
b1 )
b1 2
1.
0(
#735000
b10 7
b10 :
1(
#740000
b10 1
0.
0(
#745000
1(
#750000
b10 )
b10 2
1.
0(
#755000
b11 7
b11 :
1(
#760000
b11 1
0.
0(
#765000
1(
#770000
b11 )
b11 2
1.
0(
#775000
b100 7
b100 :
1(
#780000
b100 1
0.
0(
#785000
1(
#790000
b100 )
b100 2
1.
0(
#795000
b101 7
b101 :
1(
#800000
b101 1
0.
0(
#805000
1(
#810000
b101 )
b101 2
1.
0(
#815000
b110 7
b110 :
1(
#820000
b110 1
0.
0(
#825000
1(
#830000
b110 )
b110 2
1.
0(
#835000
b111 7
b111 :
1(
#840000
b111 1
0.
0(
#845000
1(
#850000
b111 )
b111 2
1.
0(
#855000
b1000 7
b1000 :
1(
#860000
b1000 1
0.
0(
#865000
1(
#870000
b1000 )
b1000 2
1.
0(
#875000
b1001 7
b1001 :
1(
#880000
b1001 1
0.
0(
#885000
1(
#890000
b1001 )
b1001 2
1.
0(
#895000
b1010 7
b1010 :
1(
#900000
b1010 1
0.
0(
#905000
1(
#910000
b1010 )
b1010 2
1.
0(
#915000
b1011 7
b1011 :
1(
#920000
b1011 1
0.
0(
#925000
1(
#930000
b1011 )
b1011 2
1.
0(
#935000
b1100 7
b1100 :
1(
#940000
b1100 1
0.
0(
#945000
1(
#950000
b1100 )
b1100 2
1.
0(
#955000
b1101 7
b1101 :
1(
#960000
b1101 1
0.
0(
#965000
1(
#970000
b1101 )
b1101 2
1.
0(
#975000
b1110 7
b1110 :
1(
#980000
b1110 1
0.
0(
#985000
1(
#990000
b1110 )
b1110 2
1.
0(
#995000
b1111 7
b1111 :
1(
#1000000
b1111 1
0.
0(
#1005000
1(
#1010000
b1111 )
b1111 2
1.
0(
#1015000
b10000 7
b10000 :
1(
#1020000
b10000 1
0.
0(
#1025000
1(
#1030000
b10000 )
b10000 2
1.
0(
#1035000
b10001 7
b10001 :
1(
#1040000
b10001 1
0.
0(
#1045000
1(
#1050000
b10001 )
b10001 2
1.
0(
#1055000
1"
b10010 7
b0 :
1(
#1060000
b1000100010001010101000001010100010010000011110100110001001110000010000001100011011010000110010101101001011000010010000001100001011100000110111101110011001000000011000100111000001000000110010101110011011000110111001001101001011101000110000101110011 H
b0 1
0.
0(
#1065000
1(
#1070000
1+
0(
#1075000
0"
b10001 7
b1 9
1(
#1080000
b1 1
b1100100011100100110010101101110011000010011000100111000 F
b0 D
b0 E
0+
0(
#1085000
1(
#1090000
1+
0(
#1095000
b10000 7
b10 9
b1 &
b1 8
1(
#1100000
b10 1
b1 D
b1 E
0+
0(
#1105000
1(
#1110000
1+
0(
#1115000
b1111 7
b11 9
b10 &
b10 8
1(
#1120000
b11 1
b10 D
b10 E
0+
0(
#1125000
1(
#1130000
1+
0(
#1135000
b1110 7
b100 9
b11 &
b11 8
1(
#1140000
b100 1
b11 D
b11 E
0+
0(
#1145000
1(
#1150000
1+
0(
#1155000
b1101 7
b101 9
b100 &
b100 8
1(
#1160000
b101 1
b100 D
b100 E
0+
0(
#1165000
1(
#1170000
1+
0(
#1175000
b1100 7
b110 9
b101 &
b101 8
1(
#1180000
b110 1
b101 D
b101 E
0+
0(
#1185000
1(
#1190000
1+
0(
#1195000
b1011 7
b111 9
b110 &
b110 8
1(
#1200000
b111 1
b110 D
b110 E
0+
0(
#1205000
1(
#1210000
1+
0(
#1215000
b1010 7
b1000 9
b111 &
b111 8
1(
#1220000
b1000 1
b111 D
b111 E
0+
0(
#1225000
1(
#1230000
1+
0(
#1235000
b1001 7
b1001 9
b1000 &
b1000 8
1(
#1240000
b1001 1
b1000 D
b1000 E
0+
0(
#1245000
1(
#1250000
1+
0(
#1255000
b1000 7
b1010 9
b1001 &
b1001 8
1(
#1260000
b1010 1
b1001 D
b1001 E
0+
0(
#1265000
1(
#1270000
1+
0(
#1275000
b111 7
b1011 9
b1010 &
b1010 8
1(
#1280000
b1011 1
b1010 D
b1010 E
0+
0(
#1285000
1(
#1290000
1+
0(
#1295000
b110 7
b1100 9
b1011 &
b1011 8
1(
#1300000
b1100 1
b1011 D
b1011 E
0+
0(
#1305000
1(
#1310000
1+
0(
#1315000
b101 7
b1101 9
b1100 &
b1100 8
1(
#1320000
b1101 1
b1100 D
b1100 E
0+
0(
#1325000
1(
#1330000
1+
0(
#1335000
b100 7
b1110 9
b1101 &
b1101 8
1(
#1340000
b1110 1
b1101 D
b1101 E
0+
0(
#1345000
1(
#1350000
1+
0(
#1355000
b11 7
b1111 9
b1110 &
b1110 8
1(
#1360000
b1111 1
b1110 D
b1110 E
0+
0(
#1365000
1(
#1370000
1+
0(
#1375000
b10 7
b10000 9
b1111 &
b1111 8
1(
#1380000
b10000 1
b1111 D
b1111 E
0+
0(
#1385000
1(
#1390000
1+
0(
#1395000
b1 7
b10001 9
b10000 &
b10000 8
1(
#1400000
b10001 1
b10000 D
b10000 E
0+
0(
#1405000
1(
#1410000
1+
0(
#1415000
1$
b0 7
b0 9
b10001 &
b10001 8
1(
#1420000
b100010001000101010100000101010001001000001111010011000100111000001000000111011001100001011110100110100101100001001000000110000101110000011011110111001100100000011001000111001001100101011011100110000101110010 H
b0 1
b10001 D
b10001 E
0+
0(
#1425000
1(
#1430000
b1110000100 )
b1110000100 2
1.
0(
#1435000
0$
b1 7
b1 :
1(
#1440000
b1 1
0.
0(
#1445000
1(
#1450000
b1110000101 )
b1110000101 2
1.
0(
#1455000
b10 7
b10 :
1(
#1460000
b10 1
0.
0(
#1465000
1(
#1470000
b1110000110 )
b1110000110 2
1.
0(
#1475000
b11 7
b11 :
1(
#1480000
b0 1
0.
0(
#1485000
1(
#1490000
1+
0(
#1495000
b10 7
b1 9
b1110000100 &
b1110000100 8
1(
#1500000
b1 1
b1110000011011110111001100101101011101110111001001100001011100000011000100111000 F
b1110000100 D
b1110000100 E
0+
0(
#1505000
1(
#1510000
1+
0(
#1515000
b1 7
b10 9
b1110000101 &
b1110000101 8
1(
#1520000
b10 1
b1110000101 D
b1110000101 E
0+
0(
#1525000
1(
#1530000
1+
0(
#1535000
1$
b0 7
b11 9
b1110000110 &
b1110000110 8
1(
#1540000
b11 1
b1110000110 D
b1110000110 E
0+
0(
